PyTrx/Area.py
PyTrx/CamEnv.py
PyTrx/DEM.py
PyTrx/FileHandler.py
PyTrx/Images.py
PyTrx/Line.py
PyTrx/Utilities.py
PyTrx/Velocity.py
PyTrx/__init__.py
pytrx-1.2.4.dist-info/LICENSE.txt
pytrx-1.2.4.dist-info/METADATA
pytrx-1.2.4.dist-info/WHEEL
pytrx-1.2.4.dist-info/top_level.txt
pytrx-1.2.4.dist-info/RECORD
