Metadata-Version: 2.1
Name: pytrx
Version: 1.2.4
Summary: An object-oriented toolset for calculating velocities, surface areas and distances from oblique imagery of glacial environments
Home-page: https://github.com/PennyHow/PyTrx
Author: Penelope How
Author-email: pho@geus.dk
Keywords: glaciology photogrammetry time-lapse
Classifier: Programming Language :: Python :: 3
Classifier: License :: OSI Approved :: MIT License
Classifier: Development Status :: 5 - Production/Stable
Classifier: Intended Audience :: Science/Research
Classifier: Natural Language :: English
Classifier: Operating System :: OS Independent
Requires-Python: >=3.6
License-File: LICENSE.txt
Requires-Dist: glob2
Requires-Dist: matplotlib
Requires-Dist: numpy
Requires-Dist: opencv-python (>=3)
Requires-Dist: pillow
Requires-Dist: scipy
